flask_ngrok.py
flask_ngrok-0.0.25.dist-info/METADATA
flask_ngrok-0.0.25.dist-info/RECORD
flask_ngrok-0.0.25.dist-info/WHEEL
flask_ngrok-0.0.25.dist-info/top_level.txt
