Metadata-Version: 2.1
Name: flask-ngrok
Version: 0.0.25
Summary: A simple way to demo Flask apps from your machine.
Home-page: https://github.com/gstaff/flask-ngrok
Author: Grant Stafford
License: UNKNOWN
Keywords: flask ngrok demo
Platform: UNKNOWN
Classifier: Programming Language :: Python :: 3.6
Classifier: License :: OSI Approved :: Apache Software License
Classifier: Operating System :: OS Independent
